damstrings/__init__.py
damstrings/_strings.py
damstrings-0.7.2.dist-info/LICENSE
damstrings-0.7.2.dist-info/METADATA
damstrings-0.7.2.dist-info/WHEEL
damstrings-0.7.2.dist-info/top_level.txt
damstrings-0.7.2.dist-info/RECORD
