Metadata-Version: 2.1
Name: damstrings
Version: 0.7.2
Summary: Dahmaloch's string tools
Author-email: Dahmaloch <dahmaloch@gmail.com>
Classifier: Programming Language :: Python :: 3
Classifier: License :: OSI Approved :: MIT License
Classifier: Operating System :: OS Independent
Requires-Python: >=3.9
License-File: LICENSE
Requires-Dist: Unidecode (>=1.3.4)
